arpeggio/__init__.py
arpeggio/core/__init__.py
arpeggio/core/config.py
arpeggio/core/exceptions.py
arpeggio/core/interactions.py
arpeggio/core/protein_reader.py
arpeggio/core/utils.py
arpeggio/helpers/contacts_to_graph.py
arpeggio/helpers/contacts_to_pv.py
arpeggio/helpers/show_contacts.py
arpeggio/scripts/process_protein_cli.py
pdbe_arpeggio-1.4.4.dist-info/LICENSE
pdbe_arpeggio-1.4.4.dist-info/METADATA
pdbe_arpeggio-1.4.4.dist-info/WHEEL
pdbe_arpeggio-1.4.4.dist-info/entry_points.txt
pdbe_arpeggio-1.4.4.dist-info/top_level.txt
pdbe_arpeggio-1.4.4.dist-info/RECORD
