Metadata-Version: 2.1
Name: pdbe-arpeggio
Version: 1.4.4
Summary: Arpeggio calculates interatomic contacts based on the rules defined in CREDO.
Author: Harry Jubb
Author-email: harry.jubb@sanger.ac.uk
License: GNU General Public License v3.0
Project-URL: Source code, https://github.com/PDBeurope/arpeggio
Project-URL: Documentation, https://github.com/PDBeurope/arpeggio
Project-URL: Author's repository, https://github.com/harryjubb/arpeggio
Project-URL: Paper, https://doi.org/10.1016/j.jmb.2016.12.004
Project-URL: Web server, http://biosig.unimelb.edu.au/arpeggioweb/
Keywords: arpeggio PDB contacts bioinformatics mmCIF protein ligand interactions CREDO
Classifier: Programming Language :: Python
Classifier: Programming Language :: Python :: 3
Classifier: Programming Language :: Python :: 3.6
Classifier: Programming Language :: Python :: 3.9
Classifier: Operating System :: Unix
Classifier: Operating System :: MacOS
Classifier: Operating System :: POSIX
Classifier: Intended Audience :: Science/Research
Classifier: Intended Audience :: Developers
Classifier: Topic :: Scientific/Engineering :: Bio-Informatics
Classifier: Topic :: Scientific/Engineering :: Chemistry
License-File: LICENSE
Requires-Dist: gemmi
Requires-Dist: numpy
Requires-Dist: biopython
Provides-Extra: tests
Requires-Dist: pytest ; extra == 'tests'
Requires-Dist: pytest-cov ; extra == 'tests'
